{
    "posts": [
        {
            "closed": 0, 
            "com": "Thoughts on the Nexus 4, /g/entoomen? I know some people are saying it's Troll Tier because it's LG and only 16GB, but would I be better off buying a used Galaxy Nexus + fuck off huge battery like I have right now on on Nexus S?", 
            "ext": ".png", 
            "filename": "nexus4", 
            "fsize": 95071, 
            "h": 346, 
            "md5": "5jLLRzlIWFbpuvEv56KEcA==", 
            "name": "Anonymous", 
            "no": 29127693, 
            "now": "11/16/12(Fri)19:14", 
            "resto": 0, 
            "sticky": 0, 
            "tim": 1353111250000, 
            "time": 1353111250, 
            "tn_h": 250, 
            "tn_w": 250, 
            "w": 346
        }, 
        {
            "com": "<span class=\"quote\"><a href=\"29127693#p29127693\" class=\"quotelink\">&gt;&gt;29127693</a></span><br><br>It makes calls realyl good.", 
            "name": "Anonymous", 
            "no": 29127747, 
            "now": "11/16/12(Fri)19:16", 
            "resto": 29127693, 
            "time": 1353111384
        }, 
        {
            "com": "<span class=\"quote\"><a href=\"29127693#p29127747\" class=\"quotelink\">&gt;&gt;29127747</a></span><br>Do people even make phone calls anymore, besides to taxi companies or to your carrier to complain?", 
            "name": "Anonymous", 
            "no": 29127767, 
            "now": "11/16/12(Fri)19:17", 
            "resto": 29127693, 
            "time": 1353111424
        }, 
        {
            "com": "No you wouldn't be better off getting a used Nexus.<br><br>On a related note, I'm a little agitated I have no updates on my order. At this point, I don't give a shit if it's being shipped or I have to wait 3 weeks, I just wanna know.", 
            "name": "Anonymous", 
            "no": 29127784, 
            "now": "11/16/12(Fri)19:17", 
            "resto": 29127693, 
            "time": 1353111467
        }, 
        {
            "com": "<span class=\"quote\"><a href=\"29127693#p29127767\" class=\"quotelink\">&gt;&gt;29127767</a></span><br><span class=\"quote\">&gt;has never had a job in his life</span>", 
            "name": "Anonymous", 
            "no": 29127800, 
            "now": "11/16/12(Fri)19:18", 
            "resto": 29127693, 
            "time": 1353111516
        }, 
        {
            "com": "<span class=\"quote\"><a href=\"29127693#p29127784\" class=\"quotelink\">&gt;&gt;29127784</a></span><br>If you got anything other than the 8GB by itself it'll be delayed.", 
            "name": "Anonymous", 
            "no": 29127801, 
            "now": "11/16/12(Fri)19:18", 
            "resto": 29127693, 
            "time": 1353111518
        }, 
        {
            "com": "<span class=\"quote\"><a href=\"29127693#p29127784\" class=\"quotelink\">&gt;&gt;29127784</a></span><br>Buy why, Anon? The Galaxy Nexus has a user replaceable battery so I could buy a &quot;4000&quot; mah battery from Mugen Power, giving me a 2 day battery life.", 
            "name": "Anonymous", 
            "no": 29127809, 
            "now": "11/16/12(Fri)19:19", 
            "resto": 29127693, 
            "time": 1353111540
        }, 
        {
            "com": "<span class=\"quote\"><a href=\"29127693#p29127693\" class=\"quotelink\">&gt;&gt;29127693</a></span><br>I got it today and if have to say that I really like the phone so far. Nice build, nice screen, fast performance. Looks good so far. However the speakers obviously sick for playing music but that's it.", 
            "name": "Anonymous", 
            "no": 29127811, 
            "now": "11/16/12(Fri)19:19", 
            "resto": 29127693, 
            "time": 1353111549
        }, 
        {
            "com": "<span class=\"quote\"><a href=\"29127693#p29127693\" class=\"quotelink\">&gt;&gt;29127693</a></span><br>Nexus 4 is awesome.", 
            "name": "Anonymous", 
            "no": 29127812, 
            "now": "11/16/12(Fri)19:19", 
            "resto": 29127693, 
            "time": 1353111551
        }, 
        {
            "com": "I really want to order one. Any idea when they'll be back in stock?", 
            "name": "Anonymous", 
            "no": 29127815, 
            "now": "11/16/12(Fri)19:19", 
            "resto": 29127693, 
            "time": 1353111556
        }, 
        {
            "com": "<span class=\"quote\"><a href=\"29127693#p29127693\" class=\"quotelink\">&gt;&gt;29127693</a></span><br><span class=\"quote\">&gt;only 16GB</span><br>THE CLOUD. 20,000 songs and 5GB of free data.", 
            "name": "Anonymous", 
            "no": 29127821, 
            "now": "11/16/12(Fri)19:19", 
            "resto": 29127693, 
            "time": 1353111583
        }, 
        {
            "com": "<span class=\"quote\"><a href=\"29127693#p29127800\" class=\"quotelink\">&gt;&gt;29127800</a></span><br>My boss text messages people because he knows everybody who works at my store are anti-social fuckwads who never answer the phone", 
            "name": "Anonymous", 
            "no": 29127830, 
            "now": "11/16/12(Fri)19:20", 
            "resto": 29127693, 
            "time": 1353111607
        }, 
        {
            "com": "<span class=\"quote\"><a href=\"29127693#p29127809\" class=\"quotelink\">&gt;&gt;29127809</a></span><br>The Nexus 4 has a user replaceable battery. You only need to remove two screws.", 
            "name": "Anonymous", 
            "no": 29127838, 
            "now": "11/16/12(Fri)19:20", 
            "resto": 29127693, 
            "time": 1353111629
        }, 
        {
            "com": "<span class=\"quote\"><a href=\"29127693#p29127809\" class=\"quotelink\">&gt;&gt;29127809</a></span><br>Because PowerVR SGX 540.", 
            "name": "Anonymous", 
            "no": 29127844, 
            "now": "11/16/12(Fri)19:20", 
            "resto": 29127693, 
            "time": 1353111644
        }, 
        {
            "com": "<span class=\"quote\"><a href=\"29127693#p29127821\" class=\"quotelink\">&gt;&gt;29127821</a></span><br>But I don't live in Amerifat, Anon. I only have a 6GB data plan, and there's nowhere to stream from in Canada anyway.", 
            "name": "Anonymous", 
            "no": 29127846, 
            "now": "11/16/12(Fri)19:20", 
            "resto": 29127693, 
            "time": 1353111647
        }, 
        {
            "com": "<span class=\"quote\"><a href=\"29127693#p29127809\" class=\"quotelink\">&gt;&gt;29127809</a></span><br><br>You can replace the battery on this phone too. What are the chances that you'll be able to pick up an aftermarket battery in the future?", 
            "name": "Anonymous", 
            "no": 29127850, 
            "now": "11/16/12(Fri)19:21", 
            "resto": 29127693, 
            "time": 1353111664
        }, 
        {
            "com": "<span class=\"quote\"><a href=\"29127693#p29127809\" class=\"quotelink\">&gt;&gt;29127809</a></span><br>why turn your sleek phone into a brick size device?", 
            "name": "Anonymous", 
            "no": 29127852, 
            "now": "11/16/12(Fri)19:21", 
            "resto": 29127693, 
            "time": 1353111667
        }, 
        {
            "com": "<span class=\"quote\"><a href=\"29127693#p29127838\" class=\"quotelink\">&gt;&gt;29127838</a></span><br>Yes but you can't install a bigger battery because the antennas are in the battery cover. So it's not that helpful.", 
            "name": "Anonymous", 
            "no": 29127858, 
            "now": "11/16/12(Fri)19:21", 
            "resto": 29127693, 
            "time": 1353111691
        }, 
        {
            "com": "<span class=\"quote\"><a href=\"29127693#p29127846\" class=\"quotelink\">&gt;&gt;29127846</a></span><br><span class=\"quote\">&gt;implying streaming music uses alot of data</span>", 
            "name": "Anonymous", 
            "no": 29127862, 
            "now": "11/16/12(Fri)19:21", 
            "resto": 29127693, 
            "time": 1353111704
        }, 
        {
            "com": "<span class=\"quote\"><a href=\"29127693#p29127838\" class=\"quotelink\">&gt;&gt;29127838</a></span><br>Actually, there's two screws and tape holding the battery in, so there's four screws total.<br><br>And you can't replace the backplate so there's no way to get a larger battery.", 
            "name": "Anonymous", 
            "no": 29127865, 
            "now": "11/16/12(Fri)19:21", 
            "resto": 29127693, 
            "time": 1353111706
        }, 
        {
            "com": "<span class=\"quote\"><a href=\"29127693#p29127852\" class=\"quotelink\">&gt;&gt;29127852</a></span><br>Because I care more about a good battery life than the external look of the phone.", 
            "name": "Anonymous", 
            "no": 29127878, 
            "now": "11/16/12(Fri)19:22", 
            "resto": 29127693, 
            "time": 1353111733
        }, 
        {
            "com": "<span class=\"quote\"><a href=\"29127693#p29127846\" class=\"quotelink\">&gt;&gt;29127846</a></span><br>Google play is in Canadia now.", 
            "name": "Anonymous", 
            "no": 29127881, 
            "now": "11/16/12(Fri)19:22", 
            "resto": 29127693, 
            "time": 1353111745
        }, 
        {
            "com": "<span class=\"quote\"><a href=\"29127693#p29127852\" class=\"quotelink\">&gt;&gt;29127852</a></span><br>muh freedoms", 
            "name": "Anonymous", 
            "no": 29127882, 
            "now": "11/16/12(Fri)19:22", 
            "resto": 29127693, 
            "time": 1353111746
        }, 
        {
            "com": "<span class=\"quote\"><a href=\"29127693#p29127809\" class=\"quotelink\">&gt;&gt;29127809</a></span><br>My nexus one has a user replaceable battery, and I cared a lot about this when I bought the thing<br><br>Now it's almost three years later and I've never removed the battery once.<br><br>So, fuck it, now I don't give a fuck.", 
            "name": "Anonymous", 
            "no": 29127885, 
            "now": "11/16/12(Fri)19:22", 
            "resto": 29127693, 
            "time": 1353111752
        }, 
        {
            "com": "<span class=\"quote\"><a href=\"29127693#p29127693\" class=\"quotelink\">&gt;&gt;29127693</a></span><br>I would just get a Nexus 4 unless you can get the Galaxy Nexus for very cheap.<br><br><span class=\"quote\"><a href=\"29127693#p29127838\" class=\"quotelink\">&gt;&gt;29127838</a></span><br>I think he means that with the other phone you can easily take off the entire back and get a cheap, high-capacity battery. While that may happen with the Nexus 4, it'll take a while since the antennas and Qi charging unit are in the back of it.<br><br><span class=\"quote\"><a href=\"29127693#p29127821\" class=\"quotelink\">&gt;&gt;29127821</a></span><br>Not everyone has an unlimited, uncapped data plan.<br><br><span class=\"quote\"><a href=\"29127693#p29127800\" class=\"quotelink\">&gt;&gt;29127800</a></span><br>Or maybe he only has jobs where you can contact each other in other ways.", 
            "name": "Anonymous", 
            "no": 29127897, 
            "now": "11/16/12(Fri)19:23", 
            "resto": 29127693, 
            "time": 1353111793
        }, 
        {
            "com": "<span class=\"quote\"><a href=\"29127693#p29127865\" class=\"quotelink\">&gt;&gt;29127865</a></span><br><span class=\"quote\">&gt;wanting to turn your phone into a brick</span><br>b-but muh freahduoms", 
            "name": "Anonymous", 
            "no": 29127899, 
            "now": "11/16/12(Fri)19:23", 
            "resto": 29127693, 
            "time": 1353111795
        }, 
        {
            "com": "<span class=\"quote\"><a href=\"29127693#p29127878\" class=\"quotelink\">&gt;&gt;29127878</a></span><br>If battery is such a huge factor for you then get a droid HD MAXX or whatever it's called and don't bother with anything else.", 
            "name": "Anonymous", 
            "no": 29127901, 
            "now": "11/16/12(Fri)19:23", 
            "resto": 29127693, 
            "time": 1353111805
        }, 
        {
            "com": "<span class=\"quote\"><a href=\"29127693#p29127862\" class=\"quotelink\">&gt;&gt;29127862</a></span><br>Streaming from DI.fm uses about 60MB/hour. I work for 8 hours per day, so that means 9 hours per day for just music. Oh look at that 6GB of data used in less than 12 days.", 
            "name": "Anonymous", 
            "no": 29127908, 
            "now": "11/16/12(Fri)19:23", 
            "resto": 29127693, 
            "time": 1353111812
        }, 
        {
            "com": "<span class=\"quote\"><a href=\"29127693#p29127830\" class=\"quotelink\">&gt;&gt;29127830</a></span><br>I really don't see how this is strengthening your argument.", 
            "name": "Anonymous", 
            "no": 29127909, 
            "now": "11/16/12(Fri)19:23", 
            "resto": 29127693, 
            "time": 1353111820
        }, 
        {
            "com": "I'm using it right now, liking it a lot more than I do my Atrix 4G.", 
            "name": "Anonymous", 
            "no": 29127912, 
            "now": "11/16/12(Fri)19:23", 
            "resto": 29127693, 
            "time": 1353111822
        }, 
        {
            "com": "<span class=\"quote\"><a href=\"29127693#p29127901\" class=\"quotelink\">&gt;&gt;29127901</a></span><br><br><span class=\"quote\">&gt;Verizon only</span><br><br>No.", 
            "name": "Anonymous", 
            "no": 29127923, 
            "now": "11/16/12(Fri)19:24", 
            "resto": 29127693, 
            "time": 1353111853
        }, 
        {
            "com": "<span class=\"quote\"><a href=\"29127693#p29127881\" class=\"quotelink\">&gt;&gt;29127881</a></span><br>No it's not.", 
            "name": "Anonymous", 
            "no": 29127930, 
            "now": "11/16/12(Fri)19:24", 
            "resto": 29127693, 
            "time": 1353111868
        }, 
        {
            "com": "<span class=\"quote\"><a href=\"29127693#p29127897\" class=\"quotelink\">&gt;&gt;29127897</a></span><br>Use wi-fi for most of it. And you can get a 1TB wireless hdd to store shit on.", 
            "name": "Anonymous", 
            "no": 29127931, 
            "now": "11/16/12(Fri)19:24", 
            "resto": 29127693, 
            "time": 1353111868
        }, 
        {
            "com": "<span class=\"quote\"><a href=\"29127693#p29127923\" class=\"quotelink\">&gt;&gt;29127923</a></span><br>Then don't complain faget.", 
            "name": "Anonymous", 
            "no": 29127939, 
            "now": "11/16/12(Fri)19:25", 
            "resto": 29127693, 
            "time": 1353111900
        }, 
        {
            "com": "<span class=\"quote\"><a href=\"29127693#p29127878\" class=\"quotelink\">&gt;&gt;29127878</a></span><br>why not buy a phone with large capacity initially? or better yet with battery life that meets your standards?", 
            "name": "Anonymous", 
            "no": 29127966, 
            "now": "11/16/12(Fri)19:26", 
            "resto": 29127693, 
            "time": 1353111984
        }, 
        {
            "com": "<span class=\"quote\"><a href=\"29127693#p29127966\" class=\"quotelink\">&gt;&gt;29127966</a></span><br>Name a modern smartphone with a 2 day battery life. Oh wait that's right you can't because everybody is obsessed with MOAR COARS AND GIANT SCREENS so everything has a 10 hour battery life with the stock batteries, if that.", 
            "name": "Anonymous", 
            "no": 29127984, 
            "now": "11/16/12(Fri)19:27", 
            "resto": 29127693, 
            "time": 1353112046
        }, 
        {
            "com": "<span class=\"quote\"><a href=\"29127693#p29127931\" class=\"quotelink\">&gt;&gt;29127931</a></span><br>Not everyone has a CELLULAR phone to use it predominantly on WiFi. Not many people do. And not many people want to carry an extra device with them. They'd rather pay $40-50 (Late 2012 price) for a 64GB mSD card and be done with it.<br><br>You can also buy an external battery and get 3x the life out of the phone, but people don't do that very often even when battery with an effective added battery life of 25-30Whr is only $40 on sale, and that could easily recharge your Nexus 4  to fullthree and a half times.", 
            "name": "Anonymous", 
            "no": 29127988, 
            "now": "11/16/12(Fri)19:27", 
            "resto": 29127693, 
            "time": 1353112054
        }, 
        {
            "com": "Can anyone link me to an actual good extended battery for the Galaxy Nexus?", 
            "name": "Anonymous", 
            "no": 29127989, 
            "now": "11/16/12(Fri)19:27", 
            "resto": 29127693, 
            "time": 1353112057
        }, 
        {
            "com": "<span class=\"quote\"><a href=\"29127693#p29127930\" class=\"quotelink\">&gt;&gt;29127930</a></span><br>yes it is retard", 
            "name": "Anonymous", 
            "no": 29127998, 
            "now": "11/16/12(Fri)19:28", 
            "resto": 29127693, 
            "time": 1353112082
        }, 
        {
            "com": "<span class=\"quote\"><a href=\"29127693#p29127984\" class=\"quotelink\">&gt;&gt;29127984</a></span><br>RAZR MAXX, iPhone 5, HTC One X. I don't know if those are good enough for you, but they have the best battery life of any smartphone out there.", 
            "name": "Anonymous", 
            "no": 29128000, 
            "now": "11/16/12(Fri)19:28", 
            "resto": 29127693, 
            "time": 1353112089
        }, 
        {
            "com": "<span class=\"quote\"><a href=\"29127693#p29127989\" class=\"quotelink\">&gt;&gt;29127989</a></span><br>Google &quot;Mugen Power&quot;", 
            "name": "Anonymous", 
            "no": 29128001, 
            "now": "11/16/12(Fri)19:28", 
            "resto": 29127693, 
            "time": 1353112092
        }, 
        {
            "com": "<span class=\"quote\"><a href=\"29127693#p29127984\" class=\"quotelink\">&gt;&gt;29127984</a></span><br>razr maxx<br>note 2<br><br>problem?", 
            "name": "Anonymous", 
            "no": 29128014, 
            "now": "11/16/12(Fri)19:28", 
            "resto": 29127693, 
            "time": 1353112124
        }, 
        {
            "com": "<span class=\"quote\">&gt;4600 mAh for the S3</span><br><span class=\"quote\">&gt;all these reviews saying it more than doubles your battery life for talk, screen time, etc.</span><br><br>Holy fuck. I want an S3 now.", 
            "name": "Anonymous", 
            "no": 29128017, 
            "now": "11/16/12(Fri)19:28", 
            "resto": 29127693, 
            "time": 1353112134
        }, 
        {
            "com": "<span class=\"quote\"><a href=\"29127693#p29128000\" class=\"quotelink\">&gt;&gt;29128000</a></span><br><span class=\"quote\">&gt;iphone 5</span><br><span class=\"quote\">&gt;htc one x</span><br><span class=\"quote\">&gt;good battery life</span><br><br>YAOK", 
            "name": "Anonymous", 
            "no": 29128023, 
            "now": "11/16/12(Fri)19:29", 
            "resto": 29127693, 
            "time": 1353112156
        }, 
        {
            "com": "<span class=\"quote\"><a href=\"29127693#p29128014\" class=\"quotelink\">&gt;&gt;29128014</a></span><br>Yeah, shitty nonstock Android ROMs.", 
            "name": "Anonymous", 
            "no": 29128033, 
            "now": "11/16/12(Fri)19:29", 
            "resto": 29127693, 
            "time": 1353112187
        }, 
        {
            "com": "<span class=\"quote\"><a href=\"29127693#p29127984\" class=\"quotelink\">&gt;&gt;29127984</a></span><br>galaxy note 1 and 2, htc one x+, razr maxxhd<br><br>a lot of your low teir smartphones and dumbphones have good battery life too because they dont have MOAR COARS AND GIANT SCREENS", 
            "name": "Anonymous", 
            "no": 29128037, 
            "now": "11/16/12(Fri)19:29", 
            "resto": 29127693, 
            "time": 1353112196
        }, 
        {
            "com": "<span class=\"quote\"><a href=\"29127693#p29128000\" class=\"quotelink\">&gt;&gt;29128000</a></span><br><span class=\"quote\">&gt;Longphone</span><br><span class=\"quote\">&gt;HTC One X</span><br><span class=\"quote\">&gt;good battery life</span>", 
            "ext": ".jpg", 
            "filename": "1336714294", 
            "fsize": 17015, 
            "h": 250, 
            "md5": "7a/UhHGcCX0ZF2WVne203Q==", 
            "name": "Anonymous", 
            "no": 29128044, 
            "now": "11/16/12(Fri)19:30", 
            "resto": 29127693, 
            "tim": 1353112221337, 
            "time": 1353112221, 
            "tn_h": 125, 
            "tn_w": 125, 
            "w": 250
        }, 
        {
            "com": "It would be better if you could actually buy one...", 
            "name": "Anonymous", 
            "no": 29128051, 
            "now": "11/16/12(Fri)19:30", 
            "resto": 29127693, 
            "time": 1353112231
        }, 
        {
            "com": "<span class=\"quote\"><a href=\"29127693#p29128017\" class=\"quotelink\">&gt;&gt;29128017</a></span><br><span class=\"quote\">&gt;Doubles your battery life for talk, screen time, etc.</span><br><br>That brings it just over where the iPhone 5 and HTC One X are. You may as well get a One X+ or RAZR MAXX and call it a day.", 
            "ext": ".png", 
            "filename": "51555[1]", 
            "fsize": 39151, 
            "h": 450, 
            "md5": "GAKET1VNSGljtZt+jp6z3Q==", 
            "name": "Anonymous", 
            "no": 29128057, 
            "now": "11/16/12(Fri)19:31", 
            "resto": 29127693, 
            "tim": 1353112262990, 
            "time": 1353112262, 
            "tn_h": 102, 
            "tn_w": 125, 
            "w": 550
        }, 
        {
            "com": "<span class=\"quote\"><a href=\"29127693#p29128037\" class=\"quotelink\">&gt;&gt;29128037</a></span><br>I don't want something slower than my current phone, and I don't want an old person phone.", 
            "name": "Anonymous", 
            "no": 29128066, 
            "now": "11/16/12(Fri)19:31", 
            "resto": 29127693, 
            "time": 1353112291
        }, 
        {
            "com": "<span class=\"quote\"><a href=\"29127693#p29128044\" class=\"quotelink\">&gt;&gt;29128044</a></span><br>I love my One X. Battery is pretty decent", 
            "name": "Anonymous", 
            "no": 29128068, 
            "now": "11/16/12(Fri)19:31", 
            "resto": 29127693, 
            "time": 1353112296
        }, 
        {
            "com": "I think it is very, very good. Battery life is really the only drawback, and it's comparable to for example the Galaxy S 3. You will have to charge it every night, but honestly it's not a problem. I already do that with my Galaxy S 2, which has pretty good battery life for being a smartphone.<br><br>No you're not better off with a Galaxy Nexus. The Galaxy Nexus is honestly shit compared to the Nexus 4.<br>The Nexus 4 has:<br>Much better screen (not just high res, but also full RGB instead of pentile)<br>Much much faster (The CPU is more than twice as powerful, and the GPU is also A LOT more powerful)<br>Much better camera<br>Costs the same<br>Lots of other minor stuff", 
            "name": "LAwLz", 
            "no": 29128091, 
            "now": "11/16/12(Fri)19:32", 
            "resto": 29127693, 
            "time": 1353112364, 
            "trip": "!LAwLzaWU1A"
        }, 
        {
            "com": "<span class=\"quote\"><a href=\"29127693#p29128033\" class=\"quotelink\">&gt;&gt;29128033</a></span><br><span class=\"quote\">&gt;muh custom roms</span><br><br>how are your themed stock roms?", 
            "name": "Anonymous", 
            "no": 29128095, 
            "now": "11/16/12(Fri)19:32", 
            "resto": 29127693, 
            "time": 1353112378
        }, 
        {
            "com": "<span class=\"quote\"><a href=\"29127693#p29128091\" class=\"quotelink\">&gt;&gt;29128091</a></span><br>I can get a Galaxy Nexus for $250 BNIB. A Nexus 4 (once it's in stock) will be $400 after shipping and tax.", 
            "name": "Anonymous", 
            "no": 29128105, 
            "now": "11/16/12(Fri)19:33", 
            "resto": 29127693, 
            "time": 1353112424
        }, 
        {
            "com": "<span class=\"quote\"><a href=\"29127693#p29128066\" class=\"quotelink\">&gt;&gt;29128066</a></span><br><span class=\"quote\">&gt;I don't want an old person phone.</span><br>it sounds like battery life isnt your priority", 
            "name": "Anonymous", 
            "no": 29128115, 
            "now": "11/16/12(Fri)19:34", 
            "resto": 29127693, 
            "time": 1353112456
        }, 
        {
            "com": "<span class=\"quote\"><a href=\"29127693#p29128105\" class=\"quotelink\">&gt;&gt;29128105</a></span><br>Where can you get the 16GB Galaxy Nexus for $250 after shipping and taxes? Let us all know so we can buy them.", 
            "name": "Anonymous", 
            "no": 29128120, 
            "now": "11/16/12(Fri)19:34", 
            "resto": 29127693, 
            "time": 1353112482
        }, 
        {
            "com": "<span class=\"quote\"><a href=\"29127693#p29128068\" class=\"quotelink\">&gt;&gt;29128068</a></span><br>Any idea how much an HTC One X+ costs off contract? The fuck off tiny amount of space on the North American version is pathetic.", 
            "name": "Anonymous", 
            "no": 29128128, 
            "now": "11/16/12(Fri)19:34", 
            "resto": 29127693, 
            "time": 1353112492
        }, 
        {
            "com": "<span class=\"quote\"><a href=\"29127693#p29128120\" class=\"quotelink\">&gt;&gt;29128120</a></span><br>whoops, meant to hilight <span class=\"quote\"><a href=\"29127693#p29128068\" class=\"quotelink\">&gt;&gt;29128068</a></span>", 
            "name": "Anonymous", 
            "no": 29128136, 
            "now": "11/16/12(Fri)19:35", 
            "resto": 29127693, 
            "time": 1353112523
        }, 
        {
            "com": "<span class=\"quote\"><a href=\"29127693#p29128128\" class=\"quotelink\">&gt;&gt;29128128</a></span><br>I've got the international One X so I've got 32GB of internal storage", 
            "name": "Anonymous", 
            "no": 29128139, 
            "now": "11/16/12(Fri)19:35", 
            "resto": 29127693, 
            "time": 1353112525
        }, 
        {
            "com": "So why can't Mugen just make a custom back just like they did with every other phone they made batteries for?", 
            "name": "Anonymous", 
            "no": 29128144, 
            "now": "11/16/12(Fri)19:35", 
            "resto": 29127693, 
            "time": 1353112544
        }, 
        {
            "com": "<span class=\"quote\"><a href=\"29127693#p29128120\" class=\"quotelink\">&gt;&gt;29128120</a></span><br>Craigslist, people are dumb and sell perfectly good phones for a pittance.", 
            "name": "Anonymous", 
            "no": 29128152, 
            "now": "11/16/12(Fri)19:35", 
            "resto": 29127693, 
            "time": 1353112555
        }, 
        {
            "com": "<span class=\"quote\"><a href=\"29127693#p29128144\" class=\"quotelink\">&gt;&gt;29128144</a></span><br>It'll take them time, it'll need to have antennas and the QI charger in it.", 
            "name": "Anonymous", 
            "no": 29128164, 
            "now": "11/16/12(Fri)19:36", 
            "resto": 29127693, 
            "time": 1353112586
        }, 
        {
            "com": "<span class=\"quote\"><a href=\"29127693#p29128152\" class=\"quotelink\">&gt;&gt;29128152</a></span><br>Okay, well that's a pretty bullshit comparison. I got a Nexus 4 for free because I have friends who can buy them for me. I also got a $600 laptop for $225 straight from Staples on a sale.", 
            "name": "Anonymous", 
            "no": 29128187, 
            "now": "11/16/12(Fri)19:37", 
            "resto": 29127693, 
            "time": 1353112654
        }, 
        {
            "com": "<span class=\"quote\"><a href=\"29127693#p29128091\" class=\"quotelink\">&gt;&gt;29128091</a></span><br><span class=\"quote\">&gt;The CPU is more than twice as powerful</span><br>lol, nigga lern how cores work", 
            "name": "Anonymous", 
            "no": 29128193, 
            "now": "11/16/12(Fri)19:37", 
            "resto": 29127693, 
            "time": 1353112667
        }, 
        {
            "com": "<span class=\"quote\"><a href=\"29127693#p29128144\" class=\"quotelink\">&gt;&gt;29128144</a></span><br>There's stuff on the back cover. They can still do it though.", 
            "name": "Anonymous", 
            "no": 29128200, 
            "now": "11/16/12(Fri)19:38", 
            "resto": 29127693, 
            "time": 1353112685
        }, 
        {
            "com": "<span class=\"quote\"><a href=\"29127693#p29128164\" class=\"quotelink\">&gt;&gt;29128164</a></span><br><br>That shit is actually physically built into the back cover on the phone?", 
            "name": "Anonymous", 
            "no": 29128202, 
            "now": "11/16/12(Fri)19:38", 
            "resto": 29127693, 
            "time": 1353112687
        }, 
        {
            "com": "<span class=\"quote\"><a href=\"29127693#p29128193\" class=\"quotelink\">&gt;&gt;29128193</a></span><br>It's a tripfag it's kind of expected that he'll be retarded.", 
            "name": "Anonymous", 
            "no": 29128209, 
            "now": "11/16/12(Fri)19:38", 
            "resto": 29127693, 
            "time": 1353112706
        }, 
        {
            "com": "<span class=\"quote\"><a href=\"29127693#p29128202\" class=\"quotelink\">&gt;&gt;29128202</a></span><br>yup, because Google went full Apple for the Nexus 4 and sealed the battery inside the phone.", 
            "name": "Anonymous", 
            "no": 29128220, 
            "now": "11/16/12(Fri)19:38", 
            "resto": 29127693, 
            "time": 1353112737
        }, 
        {
            "com": "<span class=\"quote\"><a href=\"29127693#p29128120\" class=\"quotelink\">&gt;&gt;29128120</a></span><br>I'll sell you one as soon as I get my Nexus 4. If you want it, send me an email and we can figure out the logistics.", 
            "email": "herpderptrashmail@gmail.com", 
            "name": "Anonymous", 
            "no": 29128222, 
            "now": "11/16/12(Fri)19:38", 
            "resto": 29127693, 
            "time": 1353112739
        }, 
        {
            "com": "<span class=\"quote\"><a href=\"29127693#p29128202\" class=\"quotelink\">&gt;&gt;29128202</a></span><br>Yeah. It was simpler to build it onto the back cover than to not. So they did.", 
            "name": "Anonymous", 
            "no": 29128228, 
            "now": "11/16/12(Fri)19:39", 
            "resto": 29127693, 
            "time": 1353112757
        }, 
        {
            "com": "<span class=\"quote\"><a href=\"29127693#p29128144\" class=\"quotelink\">&gt;&gt;29128144</a></span><br>Because bigger batteries takes up more space.<br><span class=\"quote\">&gt;Well just get a different back for the phone then.</span><br>The thing is, the Nexus 4 has lots of antennas for like NFC, wireless charging and other things inside the back panel. If a third party battery was released, they would either have to make it the same size (so that you can use the original back), or make a new back with all these extra things inside it, which would increase the cost quite a lot.", 
            "name": "LAwLz", 
            "no": 29128232, 
            "now": "11/16/12(Fri)19:39", 
            "resto": 29127693, 
            "time": 1353112770, 
            "trip": "!LAwLzaWU1A"
        }, 
        {
            "com": "<span class=\"quote\"><a href=\"29127693#p29128222\" class=\"quotelink\">&gt;&gt;29128222</a></span><br>Sure, brand new, in the box, never opened, $250 flat including shipping? I'll definitely take that.", 
            "name": "Anonymous", 
            "no": 29128236, 
            "now": "11/16/12(Fri)19:39", 
            "resto": 29127693, 
            "time": 1353112795
        }, 
        {
            "com": "<span class=\"quote\"><a href=\"29127693#p29128193\" class=\"quotelink\">&gt;&gt;29128193</a></span><br>Problem? Can you please tell me how I am wrong.", 
            "name": "LAwLz", 
            "no": 29128243, 
            "now": "11/16/12(Fri)19:40", 
            "resto": 29127693, 
            "time": 1353112809, 
            "trip": "!LAwLzaWU1A"
        }, 
        {
            "com": "<span class=\"quote\"><a href=\"29127693#p29128243\" class=\"quotelink\">&gt;&gt;29128243</a></span><br>It's probably more than twice as powerful actually.", 
            "name": "LAwLz", 
            "no": 29128263, 
            "now": "11/16/12(Fri)19:40", 
            "resto": 29127693, 
            "time": 1353112840, 
            "trip": "!LAwLzaWU1A"
        }, 
        {
            "com": "So a One X+ is $700+ shipping on eBay. Fuck that nigger shit.", 
            "name": "Anonymous", 
            "no": 29128267, 
            "now": "11/16/12(Fri)19:40", 
            "resto": 29127693, 
            "time": 1353112857
        }, 
        {
            "com": "<span class=\"quote\"><a href=\"29127693#p29128193\" class=\"quotelink\">&gt;&gt;29128193</a></span><br>Each Krait core is nearly twice as fast as the Cortex A9 cores in the GNex. If scaling was perfect, the Nexus 4 would be 4 times as fast.", 
            "name": "Anonymous", 
            "no": 29128269, 
            "now": "11/16/12(Fri)19:41", 
            "resto": 29127693, 
            "time": 1353112864
        }, 
        {
            "com": "<span class=\"quote\"><a href=\"29127693#p29128267\" class=\"quotelink\">&gt;&gt;29128267</a></span><br>Get a regular One X international. 385 - 415", 
            "name": "Anonymous", 
            "no": 29128289, 
            "now": "11/16/12(Fri)19:42", 
            "resto": 29127693, 
            "time": 1353112931
        }, 
        {
            "com": "<span class=\"quote\"><a href=\"29127693#p29128232\" class=\"quotelink\">&gt;&gt;29128232</a></span><br>OR they could, follow me here, they could make the battery a big piece that sits flush with the front half and back half of the phone and just extends the rubber ring to be a bit deeper so you can put the back cover on.<br><br>Terrible MS Paint drawing included.", 
            "ext": ".png", 
            "filename": "Nexus-4-Side", 
            "fsize": 32662, 
            "h": 475, 
            "md5": "MkOaQNjQYPpNS46AgrLkaA==", 
            "name": "Anonymous", 
            "no": 29128316, 
            "now": "11/16/12(Fri)19:43", 
            "resto": 29127693, 
            "tim": 1353112994738, 
            "time": 1353112994, 
            "tn_h": 73, 
            "tn_w": 125, 
            "w": 810
        }, 
        {
            "com": "<span class=\"quote\"><a href=\"29127693#p29128289\" class=\"quotelink\">&gt;&gt;29128289</a></span><br>Yeah I think I'll do that, and get a Mugen battery to go with it.", 
            "name": "Anonymous", 
            "no": 29128328, 
            "now": "11/16/12(Fri)19:44", 
            "resto": 29127693, 
            "time": 1353113059
        }, 
        {
            "com": "<span class=\"quote\"><a href=\"29127693#p29128316\" class=\"quotelink\">&gt;&gt;29128316</a></span><br><br>More importantly how likely is it for them to even make a battery at all?", 
            "name": "Anonymous", 
            "no": 29128351, 
            "now": "11/16/12(Fri)19:45", 
            "resto": 29127693, 
            "time": 1353113112
        }, 
        {
            "com": "<span class=\"quote\"><a href=\"29127693#p29128328\" class=\"quotelink\">&gt;&gt;29128328</a></span><br>How long do you need the battery to last? Also you can put a One X+ battery into the One X with some modding", 
            "ext": ".jpg", 
            "filename": "$(KGrHqV,!qsFBeQ!qN1IBQn+UFzw5Q~~48_20", 
            "fsize": 42022, 
            "h": 600, 
            "md5": "+d5o4HmubFGAL+HipEELIg==", 
            "name": "Anonymous", 
            "no": 29128358, 
            "now": "11/16/12(Fri)19:45", 
            "resto": 29127693, 
            "tim": 1353113128942, 
            "time": 1353113128, 
            "tn_h": 125, 
            "tn_w": 89, 
            "w": 431
        }, 
        {
            "com": "<span class=\"quote\"><a href=\"29127693#p29128328\" class=\"quotelink\">&gt;&gt;29128328</a></span><br><span class=\"quote\">&gt;Mugen battery</span><br><br>About that.", 
            "name": "Anonymous", 
            "no": 29128359, 
            "now": "11/16/12(Fri)19:45", 
            "resto": 29127693, 
            "time": 1353113129
        }, 
        {
            "com": "<span class=\"quote\"><a href=\"29127693#p29128351\" class=\"quotelink\">&gt;&gt;29128351</a></span><br>Not all that likely. They never make batteries for phones like this.", 
            "name": "Anonymous", 
            "no": 29128371, 
            "now": "11/16/12(Fri)19:46", 
            "resto": 29127693, 
            "time": 1353113164
        }, 
        {
            "com": "<span class=\"quote\"><a href=\"29127693#p29128359\" class=\"quotelink\">&gt;&gt;29128359</a></span><br><br>They have a 3200 mAh for it.", 
            "name": "Anonymous", 
            "no": 29128379, 
            "now": "11/16/12(Fri)19:46", 
            "resto": 29127693, 
            "time": 1353113193
        }, 
        {
            "com": "<span class=\"quote\"><a href=\"29127693#p29128269\" class=\"quotelink\">&gt;&gt;29128269</a></span><br><span class=\"quote\">&gt;1.5 is nearly double 1.2</span><br>lol<br>nigga<br>take a math class", 
            "name": "Anonymous", 
            "no": 29128381, 
            "now": "11/16/12(Fri)19:46", 
            "resto": 29127693, 
            "time": 1353113196
        }, 
        {
            "com": "<span class=\"quote\"><a href=\"29127693#p29128316\" class=\"quotelink\">&gt;&gt;29128316</a></span><br>but then you wouldn't want the phone, you would make a thread complaining about the thickness", 
            "name": "Anonymous", 
            "no": 29128390, 
            "now": "11/16/12(Fri)19:47", 
            "resto": 29127693, 
            "time": 1353113232
        }, 
        {
            "com": "<span class=\"quote\"><a href=\"29127693#p29128269\" class=\"quotelink\">&gt;&gt;29128269</a></span><br>Don't forget the higher clock as well.<br><br><span class=\"quote\">&gt;My face when Anon think that he is smarter than me because he knows adding more cores doesn't scale linearly.</span><br><span class=\"quote\">&gt;Calls me stupid</span><br><span class=\"quote\">&gt;Forget to take architecture and frequency difference into consideration.</span><br>I just love when people think they are being smart, look down on someone, and then realize that they themselves are actually completely wrong.<br><br><span class=\"quote\"><a href=\"29127693#p29128316\" class=\"quotelink\">&gt;&gt;29128316</a></span><br>I am not quite sure what you mean, or how that would work.<br>It is very important that the battery is not exposed. I am not sure which kind of battery they use (some new type which LG created) but some batteries, such as the one used in the iPhone, will catch fire and explore if they are punctured. So you really don't want that kind of battery exposed, or only protected by some rubber.", 
            "name": "LAwLz", 
            "no": 29128393, 
            "now": "11/16/12(Fri)19:47", 
            "resto": 29127693, 
            "time": 1353113241, 
            "trip": "!LAwLzaWU1A"
        }, 
        {
            "com": "<span class=\"quote\"><a href=\"29127693#p29128358\" class=\"quotelink\">&gt;&gt;29128358</a></span><br>Needs to last for 2 days of heavy use at a time. I don't always have time to charge it every day.", 
            "name": "Anonymous", 
            "no": 29128417, 
            "now": "11/16/12(Fri)19:48", 
            "resto": 29127693, 
            "time": 1353113311
        }, 
        {
            "com": "<span class=\"quote\"><a href=\"29127693#p29128236\" class=\"quotelink\">&gt;&gt;29128236</a></span><br>3 months old, in the box with all accessories, mint physical condition apart from a couple of minor scratches near the headphone jack and the camera bezel (not the lens). Nothing you would notice if you weren't looking for it.", 
            "name": "Anonymous", 
            "no": 29128419, 
            "now": "11/16/12(Fri)19:48", 
            "resto": 29127693, 
            "time": 1353113324
        }, 
        {
            "com": "<span class=\"quote\"><a href=\"29127693#p29128417\" class=\"quotelink\">&gt;&gt;29128417</a></span><br>Then yeah, you might need the charging case. I get 3 or so hours of screen use", 
            "name": "Anonymous", 
            "no": 29128438, 
            "now": "11/16/12(Fri)19:49", 
            "resto": 29127693, 
            "time": 1353113368
        }, 
        {
            "com": "<span class=\"quote\"><a href=\"29127693#p29128381\" class=\"quotelink\">&gt;&gt;29128381</a></span><br>Now you're just trolling.<br><br><span class=\"quote\"><a href=\"29127693#p29128393\" class=\"quotelink\">&gt;&gt;29128393</a></span><br>Double includes the clock speed boost. Krait at 700 MHz = Cortex A9 at 1.2 GHz.", 
            "name": "Anonymous", 
            "no": 29128452, 
            "now": "11/16/12(Fri)19:50", 
            "resto": 29127693, 
            "time": 1353113411
        }, 
        {
            "com": "<span class=\"quote\"><a href=\"29127693#p29128438\" class=\"quotelink\">&gt;&gt;29128438</a></span><br>It seriously only lasts for 3 hours with the stock battery? wut.", 
            "name": "Anonymous", 
            "no": 29128465, 
            "now": "11/16/12(Fri)19:51", 
            "resto": 29127693, 
            "time": 1353113460
        }, 
        {
            "com": "<span class=\"quote\"><a href=\"29127693#p29128393\" class=\"quotelink\">&gt;&gt;29128393</a></span><br><br>Goddamnit. Is there a place where I can get an international S3 for cheap? Are the international models of the S3 even good? I've been wanting to get a new phone for a year now. I'm such an indecisive fuck though. I really want it to be able to withstand heavy for more than a days use because I'm not home that much.", 
            "name": "Anonymous", 
            "no": 29128468, 
            "now": "11/16/12(Fri)19:51", 
            "resto": 29127693, 
            "time": 1353113465
        }, 
        {
            "com": "<span class=\"quote\"><a href=\"29127693#p29128390\" class=\"quotelink\">&gt;&gt;29128390</a></span><br>I would still want it, but that's just me.<br><br><span class=\"quote\"><a href=\"29127693#p29128393\" class=\"quotelink\">&gt;&gt;29128393</a></span><br>You build a shell around the battery just like you do with other extended batteries. It's just that in this case instead of building the entire back shell you build the back open and make it so you can put the Nexus 4's OEM back cover on that. The shell you make is sandwiched between the front case and the back case.<br><br><span class=\"quote\"><a href=\"29127693#p29128419\" class=\"quotelink\">&gt;&gt;29128419</a></span><br>No, thanks. $250 brand new shipped would be fine. $250 used not so much. I'll stick with the Nexus 4.", 
            "name": "Anonymous", 
            "no": 29128473, 
            "now": "11/16/12(Fri)19:51", 
            "resto": 29127693, 
            "time": 1353113474
        }, 
        {
            "com": "<span class=\"quote\"><a href=\"29127693#p29128381\" class=\"quotelink\">&gt;&gt;29128381</a></span><br>Twice the number of cores, and a faster architecture, and a 25% frequency increase.<br>Actually, I'd be surprised if it was *just* twice as powerful CPU wise. It will most likely vary from twice as fast, to maybe 5 times as fast, depending on the program.", 
            "name": "LAwLz", 
            "no": 29128483, 
            "now": "11/16/12(Fri)19:51", 
            "resto": 29127693, 
            "time": 1353113500, 
            "trip": "!LAwLzaWU1A"
        }, 
        {
            "com": "<span class=\"quote\"><a href=\"29127693#p29128393\" class=\"quotelink\">&gt;&gt;29128393</a></span><br><span class=\"quote\"><a href=\"29127693#p29128452\" class=\"quotelink\">&gt;&gt;29128452</a></span><br>look at the benchmarks niggas, its nowhere near twice as fast in cpu. gpu yea cuz that shit had a weakass gpu", 
            "name": "Anonymous", 
            "no": 29128492, 
            "now": "11/16/12(Fri)19:52", 
            "resto": 29127693, 
            "time": 1353113523
        }, 
        {
            "com": "<span class=\"quote\"><a href=\"29127693#p29128483\" class=\"quotelink\">&gt;&gt;29128483</a></span><br><span class=\"quote\">&gt;he thinks android devs know how to optimize</span>", 
            "name": "Anonymous", 
            "no": 29128508, 
            "now": "11/16/12(Fri)19:53", 
            "resto": 29127693, 
            "time": 1353113580
        }, 
        {
            "com": "<span class=\"quote\"><a href=\"29127693#p29127811\" class=\"quotelink\">&gt;&gt;29127811</a></span><br>Is your touch screen not as sensitive as you thought it would be? I keep mistyping because I'm not pressing as hard as I should be apparently compared to my old phone.", 
            "name": "Anonymous", 
            "no": 29128516, 
            "now": "11/16/12(Fri)19:53", 
            "resto": 29127693, 
            "time": 1353113595
        }, 
        {
            "com": "<span class=\"quote\"><a href=\"29127693#p29128483\" class=\"quotelink\">&gt;&gt;29128483</a></span><br>Having twice the number of cores might start to matter in two years. By then the phone's getting replaced anyway.<br><br>I'm not saying it isn't a lot faster - from what I've seen Krait gets a 30-50% increase at the same clock compared to the old A9 - but having the extra cores isn't going to help that much unless it's a TegraHD title.", 
            "name": "Anonymous", 
            "no": 29128545, 
            "now": "11/16/12(Fri)19:54", 
            "resto": 29127693, 
            "time": 1353113681
        }, 
        {
            "com": "<span class=\"quote\"><a href=\"29127693#p29128516\" class=\"quotelink\">&gt;&gt;29128516</a></span><br><span class=\"quote\"><a href=\"29127693#p29127811\" class=\"quotelink\">&gt;&gt;29127811</a></span><br><br>Can you guys make videos/take some pictures of the device. General information about your experience with it so far would be nice. Also, did it come with headphones?", 
            "name": "Anonymous", 
            "no": 29128551, 
            "now": "11/16/12(Fri)19:54", 
            "resto": 29127693, 
            "time": 1353113697
        }, 
        {
            "com": "<span class=\"quote\">&gt;chris pirillio &quot;loves&quot; the nexus 4</span><br><br>http://www.youtube.com/watch?v=jqHOcwzT5eY&amp;feature=g-u-u", 
            "name": "Anonymous", 
            "no": 29128567, 
            "now": "11/16/12(Fri)19:55", 
            "resto": 29127693, 
            "time": 1353113753
        }, 
        {
            "com": "<span class=\"quote\"><a href=\"29127693#p29128567\" class=\"quotelink\">&gt;&gt;29128567</a></span><br>chris porollo is a corporate shill", 
            "name": "Anonymous", 
            "no": 29128592, 
            "now": "11/16/12(Fri)19:56", 
            "resto": 29127693, 
            "time": 1353113812
        }, 
        {
            "com": "<a href=\"29127693#p29128468\" class=\"quotelink\">&gt;&gt;29128468</a><br><span class=\"quote\">&gt;Is there a place where I can get an international S3 for cheap?</span><br>No, because the Galaxy S 3 is not a cheap phone. You can get the international model on Newegg though.<br><br><span class=\"quote\">&gt;Black</span><br>http://www.newegg.com/Product/Product.aspx?Item=N82E16875176412<br><br><span class=\"quote\">&gt;Brown</span><br>http://www.newegg.com/Product/Product.aspx?Item=N82E16875176413<br><br><span class=\"quote\">&gt;White</span><br>http://www.newegg.com/Product/Product.aspx?Item=N82E16875176350<br><br><span class=\"quote\">&gt;Blue</span><br>http://www.newegg.com/Product/Product.aspx?Item=N82E16875176348<br><br><span class=\"quote\">&gt;Are the international models of the S3 even good?</span><br>Yes they are very good. They are slightly faster than the US version in terms of raw performance, but they got half the RAM. The international version also has a better DAC. That's the only real difference though. I am not quite sure, but the only battery test image Anand has where both the international and US version of the Galaxy S 3 are being tested, shows the international model having slightly better battery life.", 
            "name": "LAwLz", 
            "no": 29128650, 
            "now": "11/16/12(Fri)19:59", 
            "resto": 29127693, 
            "time": 1353113986, 
            "trip": "!LAwLzaWU1A"
        }, 
        {
            "com": "Any must have apps for android?", 
            "name": "Random guy from /a/", 
            "no": 29128661, 
            "now": "11/16/12(Fri)20:00", 
            "resto": 29127693, 
            "time": 1353114016
        }, 
        {
            "com": "<a href=\"29127693#p29128551\" class=\"quotelink\">&gt;&gt;29128551</a><br>Only France got headphones due to some weird law. I'll upload a couple screenshots but I'm not bringing out my camera. Too lazy. The touchscreen isn't as sensitive as I thought it would be. Depending on your preference this could be a good thing or a bad thing. There's a thread on it already on XDA: http://forum.xda-developers.com/showthread.php?t=1994628<br><br>Other than that I love it.<br><br>1/3", 
            "ext": ".png", 
            "filename": "Screenshot_2012-11-16-19-56-18", 
            "fsize": 882150, 
            "h": 1280, 
            "md5": "OeXnR3OUIRIbCVwj4sNnVw==", 
            "name": "Anonymous", 
            "no": 29128720, 
            "now": "11/16/12(Fri)20:04", 
            "resto": 29127693, 
            "tim": 1353114240127, 
            "time": 1353114240, 
            "tn_h": 125, 
            "tn_w": 75, 
            "w": 768
        }, 
        {
            "com": "<a href=\"29127693#p29128720\" class=\"quotelink\">&gt;&gt;29128720</a><br>2/3", 
            "ext": ".png", 
            "filename": "Screenshot_2012-11-16-19-58-59", 
            "fsize": 90216, 
            "h": 1280, 
            "md5": "3sRyBV4cRjV6Xz4uvTzDsA==", 
            "name": "Anonymous", 
            "no": 29128740, 
            "now": "11/16/12(Fri)20:04", 
            "resto": 29127693, 
            "tim": 1353114286128, 
            "time": 1353114286, 
            "tn_h": 125, 
            "tn_w": 75, 
            "w": 768
        }, 
        {
            "com": "<a href=\"29127693#p29128740\" class=\"quotelink\">&gt;&gt;29128740</a><br>3/3", 
            "ext": ".png", 
            "filename": "Screenshot_2012-11-16-19-58-49", 
            "fsize": 179411, 
            "h": 1280, 
            "md5": "d1yL1ykczGuTo66wUffKEA==", 
            "name": "Anonymous", 
            "no": 29128760, 
            "now": "11/16/12(Fri)20:05", 
            "resto": 29127693, 
            "tim": 1353114334243, 
            "time": 1353114334, 
            "tn_h": 125, 
            "tn_w": 75, 
            "w": 768
        }, 
        {
            "com": "<a href=\"29127693#p29128545\" class=\"quotelink\">&gt;&gt;29128545</a><br><span class=\"quote\">&gt;from what I've seen Krait gets a 30-50% increase at the same clock compared to the old A9</span><br>If we're talking raw performance, then it's more like a ~60% increase. Krait can do 3.3DMPIS/MHz, and Cortex A9 can do 2.5DMPIS/MHz.<br>The Nexus 4 has a 25% higher clock frequency though, and twice the amount of cores. All that should add up to twice the performance, if not more.<br>If you look at Linkpack benchmarks, which can be set to only run 1 thread, then you'd see that Krait at 1.5GHz is more than twice as fast as a 1.2GHz Cortex A9 (Tegra 3 in the tests I have looked at).<br><br>There are already lots of program which can take advantage of more than 2 cores on Android. MX Video player is one of them, and I am pretty sure Chrome can do it as well.<br><br>As for the GPU, the Nexus 4 utterly destroys the Galaxy nexus in that category. Hell, even my Galaxy S 2 destroys the Galaxy nexus in that category, and it's almost 2 years old now.", 
            "name": "LAwLz", 
            "no": 29128883, 
            "now": "11/16/12(Fri)20:11", 
            "resto": 29127693, 
            "time": 1353114697, 
            "trip": "!LAwLzaWU1A"
        }, 
        {
            "com": "<a href=\"29127693#p29128650\" class=\"quotelink\">&gt;&gt;29128650</a><br><br>Is there a place to get them cheaper than that? Also how is the international version better if the US version is sporting the Krait?", 
            "name": "Anonymous", 
            "no": 29129012, 
            "now": "11/16/12(Fri)20:17", 
            "resto": 29127693, 
            "time": 1353115023
        }, 
        {
            "com": "<a href=\"29127693#p29128567\" class=\"quotelink\">&gt;&gt;29128567</a><br><span class=\"quote\">&gt;Two minutes giggling about how much he likes the CRT off animation</span><br>Welcome to AOSP three years ago, Chris.", 
            "name": "Anonymous", 
            "no": 29129099, 
            "now": "11/16/12(Fri)20:20", 
            "resto": 29127693, 
            "time": 1353115247
        }, 
        {
            "com": "<a href=\"29127693#p29129012\" class=\"quotelink\">&gt;&gt;29129012</a><br><span class=\"quote\">&gt;Also how is the international version better if the US version is sporting the Krait?</span><br>Dual core Krait at 1.5 vs Quad core A9 at 1.4 GHz.<br>Krait is not quite twice as powerful (like I said before, it's &quot;only&quot; about 60% faster clock for clock) so in terms of raw performance the international one is faster (for like, movie watching if you're using software decoding, like with Hi10p content).<br>For general tasks and apps, the Krait will probably be faster.<br>Not sure about the GPU though. Too tired to look that up.", 
            "name": "LAwLz", 
            "no": 29129130, 
            "now": "11/16/12(Fri)20:22", 
            "resto": 29127693, 
            "time": 1353115324, 
            "trip": "!LAwLzaWU1A"
        }, 
        {
            "com": "<a href=\"29127693#p29128760\" class=\"quotelink\">&gt;&gt;29128760</a><br>You got a nexus 4?<br>Could you run some benchmarks?", 
            "name": "Anonymous", 
            "no": 29129131, 
            "now": "11/16/12(Fri)20:22", 
            "resto": 29127693, 
            "time": 1353115326
        }, 
        {
            "com": "<a href=\"29127693#p29129131\" class=\"quotelink\">&gt;&gt;29129131</a><br>Isn't there enough benchmarks for the Nexus 4 already?", 
            "name": "Anonymous", 
            "no": 29129149, 
            "now": "11/16/12(Fri)20:22", 
            "resto": 29127693, 
            "time": 1353115378
        }, 
        {
            "com": "<a href=\"29127693#p29129149\" class=\"quotelink\">&gt;&gt;29129149</a><br>Yeah, but those are shit.<br>I trust /g/ the most.", 
            "name": "Anonymous", 
            "no": 29129156, 
            "now": "11/16/12(Fri)20:23", 
            "resto": 29127693, 
            "time": 1353115397
        }, 
        {
            "com": "Is Mugen the best place to look for aftermarket batteries?", 
            "name": "Anonymous", 
            "no": 29129159, 
            "now": "11/16/12(Fri)20:23", 
            "resto": 29127693, 
            "time": 1353115399
        }, 
        {
            "com": "<a href=\"29127693#p29129156\" class=\"quotelink\">&gt;&gt;29129156</a><br>Give me a link to a benchmark then I guess and I'll run it.", 
            "name": "Anonymous", 
            "no": 29129184, 
            "now": "11/16/12(Fri)20:24", 
            "resto": 29127693, 
            "time": 1353115448
        }, 
        {
            "com": "<a href=\"29127693#p29129130\" class=\"quotelink\">&gt;&gt;29129130</a><br>GPU is the same Mali-400MP4 used in the SGS2. Adreno 225 is faster.<br><br>Also, the 2GB of RAM in the US version makes a big difference, especially if you have several homescreen widgets.", 
            "name": "Anonymous", 
            "no": 29129187, 
            "now": "11/16/12(Fri)20:24", 
            "resto": 29127693, 
            "time": 1353115455
        }, 
        {
            "com": "<a href=\"29127693#p29129184\" class=\"quotelink\">&gt;&gt;29129184</a><br>quadrant on the play store", 
            "name": "Anonymous", 
            "no": 29129195, 
            "now": "11/16/12(Fri)20:24", 
            "resto": 29127693, 
            "time": 1353115472
        }, 
        {
            "com": "<a href=\"29127693#p29129156\" class=\"quotelink\">&gt;&gt;29129156</a><br>benchmarks will all the be the same until a couple of updates for 4.2 come out<br>the htc DNA benches almost twice as much yet is laggier than the S3 while nexus 4 is smooth everywhere<br>benchmarks are pointless", 
            "name": "Anonymous", 
            "no": 29129206, 
            "now": "11/16/12(Fri)20:25", 
            "resto": 29127693, 
            "time": 1353115506
        }, 
        {
            "com": "<a href=\"29127693#p29129195\" class=\"quotelink\">&gt;&gt;29129195</a>", 
            "ext": ".png", 
            "filename": "Screenshot_2012-11-16-20-26-52", 
            "fsize": 120462, 
            "h": 1280, 
            "md5": "joIl89dr3E87jiyt73BX1Q==", 
            "name": "Anonymous", 
            "no": 29129260, 
            "now": "11/16/12(Fri)20:27", 
            "resto": 29127693, 
            "tim": 1353115645733, 
            "time": 1353115645, 
            "tn_h": 125, 
            "tn_w": 75, 
            "w": 768
        }, 
        {
            "com": "<a href=\"29127693#p29129260\" class=\"quotelink\">&gt;&gt;29129260</a><br>Thanks bro.", 
            "name": "Anonymous", 
            "no": 29129266, 
            "now": "11/16/12(Fri)20:27", 
            "resto": 29127693, 
            "time": 1353115665
        }, 
        {
            "com": "So apparently if you log into a Box account from your Nexus 4 you get 50GB free. I've never used Box. How is it compared to Dropbox? The fact I got 50GB free makes me want to use it more than Dropbox.", 
            "name": "Anonymous", 
            "no": 29129310, 
            "now": "11/16/12(Fri)20:30", 
            "resto": 29127693, 
            "time": 1353115800
        }, 
        {
            "com": "<a href=\"29127693#p29129260\" class=\"quotelink\">&gt;&gt;29129260</a><br>Oh god that memory bandwidth. It's delicious. <br><br>Basemark Taiji, please.", 
            "name": "Anonymous", 
            "no": 29129323, 
            "now": "11/16/12(Fri)20:30", 
            "resto": 29127693, 
            "time": 1353115830
        }, 
        {
            "com": "<a href=\"29127693#p29129323\" class=\"quotelink\">&gt;&gt;29129323</a><br>This one? https://play.google.com/store/apps/details?id=com.rightware.tdmm2v10jnifree&amp;feature=search_resul<br>t", 
            "name": "Anonymous", 
            "no": 29129345, 
            "now": "11/16/12(Fri)20:31", 
            "resto": 29127693, 
            "time": 1353115871
        }, 
        {
            "com": "<a href=\"29127693#p29129310\" class=\"quotelink\">&gt;&gt;29129310</a><br>It's got some bullshit limit like 100 mb per file. Got an account with my Touchpad, it's useless.", 
            "name": "Anonymous", 
            "no": 29129355, 
            "now": "11/16/12(Fri)20:31", 
            "resto": 29127693, 
            "time": 1353115891
        }, 
        {
            "com": "<a href=\"29127693#p29129345\" class=\"quotelink\">&gt;&gt;29129345</a><br>Yes. Oh god I'm so jelly.", 
            "name": "Anonymous", 
            "no": 29129366, 
            "now": "11/16/12(Fri)20:32", 
            "resto": 29127693, 
            "time": 1353115934
        }, 
        {
            "com": "HERE WE GO AGAIN X4<br>alright /g/ it\u2019s hurting me to see you struggle like this over all these years, so rather than just treat this as a comedy board as usual I'm going to give you some actual knowledge:<br><br>THE ONLY FEATURE THAT MATTERS ON THE LATEST GENERATION OF CELL PHONES IS: ...battery life<br><br>Your phones features don't mean shit if your phones dead before an 8 hour work day!<br>I've ready countless threads about which snap dragon dildo processor or rectum retina display you need or you just don't know shit about technology- NO. all new phones run the latest apps, they all browse relatively quickly on your respective network.<br><br>But if you purchase a dead beat battery phone you're disqualified.<br>Don\u2019t care about its feature, don't care about the price, don't care about the contract, if its off, its useless to me.<br><br>I'll let /g/ get back to ranting and raving over the next best i52500k cyber sex Monday /g/eentoo OS or whatever the buzzwords are these days now.", 
            "ext": ".png", 
            "filename": "battery", 
            "fsize": 34858, 
            "h": 404, 
            "md5": "RVrnu3hxs73ESvitTEFHog==", 
            "name": "Anonymous", 
            "no": 29129380, 
            "now": "11/16/12(Fri)20:32", 
            "resto": 29127693, 
            "tim": 1353115972892, 
            "time": 1353115972, 
            "tn_h": 67, 
            "tn_w": 124, 
            "w": 743
        }
    ]
}
